MANIFEST.in
README.md
setup.py
django_formrenderer.egg-info/PKG-INFO
django_formrenderer.egg-info/SOURCES.txt
django_formrenderer.egg-info/dependency_links.txt
django_formrenderer.egg-info/requires.txt
django_formrenderer.egg-info/top_level.txt
formrenderer/__init__.py
formrenderer/templates/formrenderer/as_p.html
formrenderer/templates/formrenderer/as_table.html
formrenderer/templates/formrenderer/as_ul.html
formrenderer/templates/formrenderer/default.html
formrenderer/templates/formrenderer/bootstrap/horizontal.html
formrenderer/templates/formrenderer/bootstrap/horizontal_checkbox.html
formrenderer/templates/formrenderer/bootstrap/horizontal_date.html
formrenderer/templates/formrenderer/bootstrap/horizontal_dollars.html
formrenderer/templates/formrenderer/bootstrap/horizontal_nohelp.html
formrenderer/templates/formrenderer/bootstrap/horizontal_percent.html
formrenderer/templates/formrenderer/bootstrap/inline_nolabels.html
formrenderer/templates/formrenderer/bootstrap/stacked.html
formrenderer/templatetags/__init__.py
formrenderer/templatetags/renderform.py