Metadata-Version: 1.0
Name: django-formrenderer
Version: 2.0
Summary: A reusable django app for customising form rendering from your template.
Home-page: https://github.com/humphrey/django_formrenderer
Author: Humphrey Murray (Datalive Software)
Author-email: hmurray@datalive.com.au
License: UNKNOWN
Platform: UNKNOWN
Classifier: Operating System :: OS Independent
Classifier: Programming Language :: Python
Classifier: Framework :: Django
